{
  "info": {
    "_postman_id": "c0cabd0b-f9d8-4507-bce4-f086e813abae",
    "name": "CRUD API Chaining",
    "schema": "https://schema.getpostman.com/json/collection/v2.1.0/collection.json",
    "_exporter_id": "29629244",
    "_collection_link": "https://go.postman.co/collection/29629244-c0cabd0b-f9d8-4507-bce4-f086e813abae?source=collection_link"
  },
  "item": [
    {
      "name": "Creat user",
      "event": [
        {
          "listen": "test",
          "script": {
            "exec": [
              "let response = pm.response.json();\r",
              "\r",
              "pm.collectionVariables.set(\"userId\", response.user.id);"
            ],
            "type": "text/javascript",
            "packages": {},
            "requests": {}
          }
        }
      ],
      "request": {
        "method": "POST",
        "header": [],
        "body": {
          "mode": "raw",
          "raw": "{\r\n    \"name\": \"Ilyas Farhan\",\r\n    \"email\":\"ilyas@gmail.com\",\r\n    \"job role\": \"Technical support specialist\"\r\n}",
          "options": {
            "raw": {
              "language": "json"
            }
          }
        },
        "url": {
          "raw": "http://localhost:3001/users",
          "protocol": "http",
          "host": [
            "localhost"
          ],
          "port": "3001",
          "path": [
            "users"
          ]
        }
      },
      "response": []
    },
    {
      "name": "Get user using var",
      "protocolProfileBehavior": {
        "disableBodyPruning": true
      },
      "request": {
        "method": "GET",
        "header": [],
        "body": {
          "mode": "raw",
          "raw": "{\r\n    \"name\": \"Ilyas Farhan\",\r\n    \"email\":\"ilyas@gmail.com\",\r\n    \"job role\": \"Technical support specialist\"\r\n}"
        },
        "url": {
          "raw": "http://localhost:3001/users/{{userId}}",
          "protocol": "http",
          "host": [
            "localhost"
          ],
          "port": "3001",
          "path": [
            "users",
            "{{userId}}"
          ]
        }
      },
      "response": []
    },
    {
      "name": "Update user using var",
      "request": {
        "auth": {
          "type": "noauth"
        },
        "method": "PUT",
        "header": [],
        "body": {
          "mode": "raw",
          "raw": "{\r\n    \"name\": \"Syed Ilyas Sheikh\",\r\n    \"email\":\"ilyas321@gmail.com\",\r\n    \"age\": \"25\"\r\n}",
          "options": {
            "raw": {
              "language": "json"
            }
          }
        },
        "url": {
          "raw": "http://localhost:3001/users/{{userId}}",
          "protocol": "http",
          "host": [
            "localhost"
          ],
          "port": "3001",
          "path": [
            "users",
            "{{userId}}"
          ]
        }
      },
      "response": []
    },
    {
      "name": "Del user using var",
      "request": {
        "auth": {
          "type": "noauth"
        },
        "method": "DELETE",
        "header": [],
        "body": {
          "mode": "raw",
          "raw": "{\r\n    \"name\": \"Syed Ilyas Sheikh\",\r\n    \"email\":\"ilyas321@gmail.com\",\r\n    \"age\": \"25\"\r\n}"
        },
        "url": {
          "raw": "http://localhost:3001/users/{{userId}}",
          "protocol": "http",
          "host": [
            "localhost"
          ],
          "port": "3001",
          "path": [
            "users",
            "{{userId}}"
          ]
        }
      },
      "response": []
    }
  ],
  "variable": [
    {
      "key": "userId",
      "value": ""
    }
  ]
}